agora_logging/__init__.py
agora_logging/agora_logger.py
agora_logging/colored_text.py
agora_logging/log_level.py
agora_logging/version.py
agora_logging/handlers/__init__.py
agora_logging/handlers/base_handler.py
agora_logging/handlers/stream_handler.py
agora_logging-3.0.2.dist-info/licenses/LICENSE
agora_logging-3.0.2.dist-info/WHEEL
agora_logging-3.0.2.dist-info/METADATA
agora_logging-3.0.2.dist-info/RECORD
